{"task": "materials", "video_path": "videos/level_1/56195/clip_31.mp4", "item_id": "56195_clip_31_materials", "gold": "A", "note": "```json\n{\n  \"key_evidence\": [\"A clear liquid is being transferred from a tube into a petri dish, suggesting the handling of biological material.\", \"The petri dish contains a medium that appears to be suitable for culturing living entities.\"],\n  \"context_observations\": [\"The procedure is taking place in a sterile environment, likely a biosafety cabinet.\", \"The person is wearing gloves, indicating the need for aseptic technique.\"],\n  \"salient_objects_or_text\": [\"A pipette is used for transferring the liquid.\", \"A petri dish with a visible medium is present.\", \"A tube with a blue cap is being used as the source of the liquid.\"]\n}\n```"}