{"video_id": "videos/level_1/62182/clip_47.mp4", "task": "operation", "note": "```json\n{\n  \"actions_performed\": [\n    \"pipette 100uL from bottle into well A1\",\n    \"place pipette back into rack\",\n    \"open incubator door\",\n    \"retrieve sample from incubator\"\n  ],\n  \"objects_manipulated\": [\n    \"pipette\",\n    \"bottle\",\n    \"well A1\",\n    \"incubator\"\n  ],\n  \"tool_object_interaction\": [\n    \"pipette\u5438\u53d6100\u5fae\u5347\u6db2\u4f53\u5e76\u6ce8\u5165A1\u5b54\u4e2d\",\n    \"pipette\u653e\u7f6e\u56de\u67b6\u5b50\u4e0a\",\n    \"\u6253\u5f00\u5b75\u5316\u5668\u95e8\",\n    \"\u4ece\u5b75\u5316\u5668\u4e2d\u53d6\u51fa\u6837\u672c\"\n  ]\n}\n```"}