{"video_id": "videos/level_2/video_segments/61800/clip_4.mp4", "task": "sequence_generation", "note": "```json\n{\n  \"observed_steps_in_order\": [\n    \"Prepare a sample slide\",\n    \"Apply a drop of liquid to the slide\",\n    \"Cover the sample with a cover slip\",\n    \"Place the slide under the microscope\"\n  ],\n  \"key_actions_per_step\": [\n    \"Hold a slide and dropper\",\n    \"Dip dropper into liquid container and apply drop to slide\",\n    \"Use fingers to place cover slip over the drop\",\n    \"Slide the prepared slide onto the microscope stage\"\n  ],\n  \"materials_or_tools_used\": [\n    \"Microscope\",\n    \"Sample slide\",\n    \"Cover slip\",\n    \"Liquid dropper\",\n    \"Liquid container\"\n  ]\n}\n```"}