{"video_id": "videos/level_2/video_segments/61854/clip_7.mp4", "task": "sequence_generation", "note": "```json\n{\n  \"observed_steps_in_order\": [\n    \"Transfer liquid from a pipette to a petri dish\",\n    \"Place the petri dish under a microscope\",\n    \"Analyze the sample using a computer\"\n  ],\n  \"key_actions_per_step\": [\n    \"Use a pipette to transfer liquid into a petri dish\",\n    \"Position the petri dish under a microscope\",\n    \"Operate a computer with specialized software to analyze the sample\"\n  ],\n  \"materials_or_tools_used\": [\n    \"Pipette\",\n    \"Petri dish\",\n    \"Microscope\",\n    \"Computer with specialized software\"\n  ]\n}\n```"}