{"video_id": "videos/level_2/video_segments/61062/clip_2.mp4", "task": "sequence_ordering", "note": "```json\n{\n  \"observed_steps_in_order\": [\n    \"adjust the pipette volume\",\n    \"pipette liquid into a microtube\",\n    \"pipette liquid into a multi-well plate\"\n  ],\n  \"first_step\": \"adjust the pipette volume\",\n  \"last_step\": \"pipette liquid into a multi-well plate\",\n  \"key_transitions\": [\n    \"after adjusting the pipette, the liquid is transferred into a microtube\",\n    \"after filling the microtube, the pipette is used to transfer liquid into a multi-well plate\"\n  ]\n}\n```"}