{"video_id": "videos/level_2/video_segments/61037/clip_7.mp4", "task": "sequence_ordering", "note": "```json\n{\n  \"observed_steps_in_order\": [\n    \"step 1 description: A scientist places a gel into a gel box containing a buffer solution.\",\n    \"step 2 description: The scientist pours a liquid from a bottle into a tray containing a gel.\",\n    \"step 3 description: The scientist places a gel into a tray containing a liquid.\",\n    \"step 4 description: The scientist pours a liquid from a bottle into a beaker.\",\n    \"step 5 description: The scientist places a gel into a tray containing a liquid.\"\n  ],\n  \"first_step\": \"A scientist places a gel into a gel box containing a buffer solution.\",\n  \"last_step\": \"The scientist places a gel into a tray containing a liquid.\",\n  \"key_transitions\": [\n    \"The scientist transitions from placing a gel into a gel box to pouring a liquid into a tray.\",\n    \"The scientist transitions from pouring a liquid into a tray to placing a gel into a tray.\",\n    \"The scientist transitions from placing a gel into a tray to pouring a liquid into a beaker.\",\n    \"The scientist transitions from pouring a liquid into a beaker to placing a gel into a tray.\"\n  ]\n}\n```"}