{"task": "step_prediction", "video_path": "videos/level_2/step_prediction/57629/clip_1_prediction.mp4", "item_id": "57629_clip_1_step_prediction", "gold": "5", "note": "```json\n{\n  \"observed_steps_so_far\": [\n    \"A rodent is shown with its abdomen opened, exposing internal organs.\",\n    \"A pair of scissors is used to cut away tissue near the stomach area.\",\n    \"A ruler is placed next to the rodent, indicating a measurement is being taken.\"\n  ],\n  \"current_state_at_end_with_evidence\": \"The rodent's abdomen is open, and a segment of the intestine is visible and appears to have been cut. The ruler suggests a measurement of the intestine has been taken, which aligns with the need to remove a specific length of intestine as the next step.\",\n  \"salient_objects_or_text\": [\n    \"A ruler with centimeter markings\",\n    \"A pair of scissors\",\n    \"A yellow syringe cap\"\n  ]\n}\n```"}