{"video_id": "videos/level_3/57332_.mp4", "task": "scientific_discovery", "note": "```json\n{\n  \"experiment_overview\": \"The experiment appears to focus on the analysis of various environmental and chemical parameters in agricultural settings, specifically comparing data from commercial barns, simulated bedded packs, and using static and dynamic flux chamber methods. The data includes measurements of dry matter, total nitrogen, phosphorus, sulfur, potassium, ash, lignin, carbon-to-nitrogen ratio, pH, temperature, and various gas emissions such as ammonia, total reduced sulfur, hydrogen sulfide, carbon dioxide, methane, and nitrous oxide.\",\n  \"novel_techniques_shown\": [\n    \"Use of static and dynamic flux chamber methods for measuring gas emissions.\",\n    \"Simulated bedded packs for controlled environmental analysis.\"\n  ],\n  \"key_steps\": [\n    \"Collection of samples from commercial barns and simulated bedded packs.\",\n    \"Measurement of various chemical and physical properties of the samples.\",\n    \"Use of flux chambers to measure gas emissions.\",\n    \"Data recording and analysis using computer software.\"\n  ],\n  \"materials_subjects\": [\n    \"Samples from commercial barns.\",\n    \"Simulated bedded packs.\",\n    \"Various chemical and environmental samples for analysis.\"\n  ],\n  \"tools_and_setup\": [\n    \"Flux chambers (static and dynamic).\",\n    \"Computer software for data recording and analysis.\",\n    \"Laboratory equipment for measuring chemical and physical properties.\"\n  ],\n  \"anything_unusual_or_notable\": [\n    \"The use of both static and dynamic flux chamber methods suggests a comprehensive approach to measuring gas emissions.\",\n    \"The comparison between commercial barns and simulated bedded packs indicates a focus on understanding the impact of different agricultural practices.\"\n  ]\n}\n```"}