{"video_id": "videos/level_3/52653_.mp4", "task": "experimental_conclusion", "note": "```json\n{\n  \"experiment_overview\": \"The experiment involves applying a stereotactic injection technique to study the genetic effects on animal behaviors, specifically focusing on the impact of RBM8a gene knockdown in mice.\",\n  \"procedures_observed\": [\n    \"A mouse is anesthetized and placed in a stereotactic frame.\",\n    \"A small incision is made on the mouse's scalp to expose the skull.\",\n    \"A stereotactic injection is performed, likely targeting a specific brain region.\",\n    \"The mouse is then placed in an open field for behavioral observation.\",\n    \"Data is collected and analyzed, comparing the behavior of the control and RBM8a knockdown groups.\"\n  ],\n  \"materials_and_subjects\": [\n    \"Mice (control and RBM8a knockdown groups)\",\n    \"Anesthetic solution\",\n    \"Surgical instruments for incision\",\n    \"Stereotactic frame and injection apparatus\",\n    \"Open field for behavioral testing\"\n  ],\n  \"tools_and_setup\": [\n    \"Stereotactic frame\",\n    \"Injection apparatus\",\n    \"Surgical instruments\",\n    \"Open field arena\",\n    \"Computer for data analysis\"\n  ],\n  \"quantitative_observations\": [\n    \"Time (sec) for floating behavior: Control group - approximately 100 sec, RBM8a knockdown group - approximately 40 sec.\"\n  ],\n  \"outcomes_visible\": [\n    \"The RBM8a knockdown group showed a significant reduction in floating time compared to the control group, indicating altered behavior due to the genetic modification.\"\n  ]\n}\n```"}