{"video_id": "videos/level_2/video_segments/55301/clip_1.mp4", "task": "sequence_ordering", "note": "```json\n{\n  \"observed_steps_in_order\": [\n    \"A person wearing purple gloves sprinkles a substance into a pot of soil.\",\n    \"The scene shifts to a container with a white substrate where small insects are present.\",\n    \"The video then shows a tray of young plants growing in soil.\",\n    \"A person wearing purple gloves places trays of young plants into a growth chamber.\"\n  ],\n  \"first_step\": \"A person wearing purple gloves sprinkles a substance into a pot of soil.\",\n  \"last_step\": \"A person wearing purple gloves places trays of young plants into a growth chamber.\",\n  \"key_transitions\": [\n    \"The scene transitions from a pot of soil to a container with a white substrate.\",\n    \"The scene transitions from a container with a white substrate to a tray of young plants.\",\n    \"The scene transitions from a tray of young plants to a growth chamber.\"\n  ]\n}\n```"}