{"video_id": "videos/level_2/video_segments/59156/clip_8.mp4", "task": "sequence_ordering", "note": "```json\n{\n  \"observed_steps_in_order\": [\n    \"A scientist uses a pipette to transfer a liquid onto a slide under a microscope.\",\n    \"The scientist examines the sample through the microscope.\",\n    \"The scientist places a petri dish into an incubator.\"\n  ],\n  \"first_step\": \"A scientist uses a pipette to transfer a liquid onto a slide under a microscope.\",\n  \"last_step\": \"The scientist places a petri dish into an incubator.\",\n  \"key_transitions\": [\n    \"The transition from examining the sample under the microscope to placing the petri dish into the incubator is implied by the change in focus from the microscope to the incubator.\"\n  ]\n}\n```"}