{"video_id": "videos/level_2/video_segments/58332/clip_9.mp4", "task": "sequence_ordering", "note": "```json\n{\n  \"observed_steps_in_order\": [\n    \"Transfer liquid from a pipette into a test tube.\",\n    \"Place the test tube into an orange test tube rack.\",\n    \"Close the test tube with a cap.\",\n    \"Place the test tube rack into a centrifuge.\"\n  ],\n  \"first_step\": \"Transfer liquid from a pipette into a test tube.\",\n  \"last_step\": \"Place the test tube rack into a centrifuge.\",\n  \"key_transitions\": [\n    \"The test tube is placed into the test tube rack after being filled with liquid.\",\n    \"The test tube rack is then placed into the centrifuge after being closed.\"\n  ]\n}\n```"}