{"video_id": "videos/level_2/video_segments/61231/clip_7.mp4", "task": "sequence_ordering", "note": "```json\n{\n  \"observed_steps_in_order\": [\n    \"Transfer liquid from a pipette into a test tube.\",\n    \"Cap the test tube.\",\n    \"Place the test tube into a centrifuge.\"\n  ],\n  \"first_step\": \"Transfer liquid from a pipette into a test tube.\",\n  \"last_step\": \"Place the test tube into a centrifuge.\",\n  \"key_transitions\": [\n    \"The test tube is capped after the liquid transfer.\",\n    \"The test tube is then placed into the centrifuge.\"\n  ]\n}\n```"}