{"video_id": "videos/level_2/video_segments/52299/clip_3.mp4", "task": "sequence_ordering", "note": "```json\n{\n  \"observed_steps_in_order\": [\n    \"Pouring liquid into a petri dish.\",\n    \"Placing a small piece of tissue onto a petri dish using tweezers.\",\n    \"Using tweezers to manipulate the tissue within the petri dish.\",\n    \"Examining a large, dissected organ under a microscope.\"\n  ],\n  \"first_step\": \"Pouring liquid into a petri dish.\",\n  \"last_step\": \"Examining a large, dissected organ under a microscope.\",\n  \"key_transitions\": [\n    \"The transition from pouring liquid to placing tissue is implied by the change in focus from the liquid to the tissue.\",\n    \"The transition from manipulating the tissue to examining the organ is marked by the shift in the object being observed and the use of a different tool (microscope).\"\n  ]\n}\n```"}