{"video_id": "videos/level_2/video_segments/54786/clip_7.mp4", "task": "sequence_ordering", "note": "```json\n{\n  \"observed_steps_in_order\": [\n    \"A gloved hand places a bottle labeled 'Cultured Endothelial Cell Growth Medium' into a red tube rack.\",\n    \"The same gloved hand opens a refrigerator and retrieves a container.\",\n    \"The container is placed inside an Eppendorf centrifuge.\",\n    \"The centrifuge door is closed and the centrifuge is turned on.\",\n    \"A gloved hand uses a pipette to transfer liquid from one container to another.\",\n    \"The liquid is dispensed into a test tube holder.\",\n    \"The test tube holder is placed into a freezer.\"\n  ],\n  \"first_step\": \"A gloved hand places a bottle labeled 'Cultured Endothelial Cell Growth Medium' into a red tube rack.\",\n  \"last_step\": \"The test tube holder is placed into a freezer.\",\n  \"key_transitions\": [\n    \"The transition from placing the bottle into the tube rack to opening the refrigerator and retrieving the container.\",\n    \"The transition from retrieving the container to placing it inside the centrifuge.\",\n    \"The transition from closing the centrifuge door to turning it on.\",\n    \"The transition from using the pipette to transfer liquid to dispensing the liquid into the test tube holder.\",\n    \"The transition from placing the test tube holder into the freezer.\"\n  ]\n}\n```"}