{"video_id": "videos/level_1/50484/clip_31.mp4", "task": "quantity", "note": "```json\n{\n  \"numbers_visible\": [\n    \"250\",\n    \"1\",\n    \"1\",\n    \"1344\",\n    \"1024\",\n    \"2\",\n    \"2\",\n    \"672\",\n    \"512\",\n    \"4\",\n    \"4\",\n    \"336\",\n    \"256\",\n    \"8\",\n    \"8\",\n    \"168\",\n    \"128\",\n    \"0.10\",\n    \"0.10\",\n    \"152\",\n    \"490\",\n    \"0\"\n  ],\n  \"counts\": [\n    \"1 camera control window\",\n    \"1 dropdown menu for binning\",\n    \"1 checkbox for 'Adjust with binning'\",\n    \"1 checkbox for 'Show saturation'\",\n    \"1 checkbox for 'Automatic'\",\n    \"1 checkbox for 'Online Histogram'\",\n    \"1 slider for 'Min'\",\n    \"1 slider for 'Max'\",\n    \"1 text box for 'Min'\",\n    \"1 text box for 'Max'\",\n    \"1 text box for 'Offset'\"\n  ],\n  \"measurements_observed\": [\n    \"Exposure time: 250 ms\",\n    \"Binning options with dimensions (e.g., 1344 x 1024, 672 x 512, etc.)\",\n    \"Brightness adjustment percentages: Min 0.10%, Max 0.10%\",\n    \"Brightness adjustment values: Min 152, Max 490\"\n  ]\n}\n```"}