{"video_id": "videos/level_1/56651/clip_55.mp4", "task": "materials", "note": "```json\n{\n  \"materials_visible\": [\"0.5 M Tris\", \"anti-rabbit ATF3\"],\n  \"labels_seen\": [\"Wash 3x 0.5 M Tris 10 min/wash\", \"1:100 anti-rabbit ATF3\"],\n  \"container_descriptions\": [\"White multi-well tray with transparent compartments\", \"Small white tube held in hand\"],\n  \"substance_appearance\": [\"Clear liquid in the multi-well tray compartments\", \"Clear liquid in the small white tube\"]\n}\n```"}