{"video_id": "videos/level_1/54664/clip_13.mp4", "task": "materials", "note": "```json\n{\n  \"materials_visible\": [\"yellow liquid\"],\n  \"labels_seen\": [\"8 min 7,500 x g\", \"Eppendorf Centrifuge 5417C\"],\n  \"container_descriptions\": [\"round-bottom flask with a narrow neck, clear glass, medium size\", \"test tubes, clear plastic, small size, arranged in a pink rack\", \"cork base supporting the round-bottom flask\"],\n  \"substance_appearance\": [\"yellow liquid, liquid state, clear texture\"]\n}\n```"}