{"video_id": "videos/level_1/4295/clip_12.mp4", "task": "operation", "note": "```json\n{\n  \"actions_performed\": [\n    \"transfers a rectangular object from a container to aluminum foil\"\n  ],\n  \"objects_manipulated\": [\n    \"rectangular object\",\n    \"aluminum foil\",\n    \"container\"\n  ],\n  \"tool_object_interaction\": [\n    \"gloved hands pick up the rectangular object from the container\",\n    \"gloved hands place the rectangular object onto the aluminum foil\"\n  ]\n}\n```"}