{"video_id": "videos/level_3/3521_.mp4", "task": "experimental_conclusion", "note": "```json\n{\n  \"experiment_overview\": \"The experiment involves culturing, infecting, and aggregating cells to study their behavior under hypoxic conditions using fluorescent signaling.\",\n  \"procedures_observed\": [\n    \"Cells are cultured in a petri dish.\",\n    \"A centrifuge is used to separate cells from the medium.\",\n    \"Cells are placed into a chamber for hypoxic conditions.\",\n    \"Fluorescent signaling is observed under a microscope.\"\n  ],\n  \"materials_and_subjects\": [\n    \"Cells (likely cancerous or stem cells)\",\n    \"Petri dishes\",\n    \"Centrifuge tubes\",\n    \"Centrifuge\",\n    \"Chamber for hypoxic conditions\",\n    \"Microscope\"\n  ],\n  \"tools_and_setup\": [\n    \"Microscope\",\n    \"Centrifuge\",\n    \"Petri dishes\",\n    \"Chamber for hypoxic conditions\",\n    \"Microscope slides\",\n    \"Microscope objective lenses\"\n  ],\n  \"quantitative_observations\": [\n    \"5 min, 130 x g centrifugation time\",\n    \"12 hrs, 24 hrs, 96 hrs time points for observation\"\n  ],\n  \"outcomes_visible\": [\n    \"Cells are shown in a petri dish at different time points (12 hrs, 24 hrs, 96 hrs).\",\n    \"Fluorescent signaling is observed under the microscope, indicating hypoxic conditions.\"\n  ]\n}\n```"}