{"task": "sequence_generation", "video_path": "videos/level_2/video_segments/55858/clip_9.mp4", "item_id": "55858_clip9_sequence_generation", "gold": ["35", "36", "37", "38", "39"], "note": "```json\n{\n  \"observed_steps_with_evidence\": [\n    \"A reducing potential of -0.8 V is set on the control interface, as seen on the digital display.\",\n    \"A syringe is used to inject a gas into a vial containing a solution, indicating the saturation of the buffer with a gas.\",\n    \"A peristaltic pump speed controller is adjusted, suggesting the initiation of buffer flow through the system.\",\n    \"A graph on the computer screen shows a gradual change over time, likely representing the activation process under flowing conditions.\",\n    \"The computer screen displays a spectrum acquisition interface, indicating the collection of an absorption spectrum.\"\n  ],\n  \"salient_objects_or_text\": [\n    \"Control interface showing -0.8 V potential setting\",\n    \"Syringe injecting gas into a vial\",\n    \"Peristaltic pump speed controller labeled 'QL-1000'\",\n    \"Graph on computer screen showing data over time\",\n    \"Spectrum acquisition interface on computer screen\"\n  ]\n}\n```"}