{"video_id": "videos/level_1/56997/clip_25.mp4", "task": "materials", "note": "```json\n{\n  \"materials_visible\": [\n    \"agar\",\n    \"microscope slides\",\n    \"pipette tips\"\n  ],\n  \"labels_seen\": [\n    \"jove\"\n  ],\n  \"container_descriptions\": [\n    {\n      \"shape\": \"petri dish\",\n      \"color\": \"transparent\",\n      \"size\": \"small\"\n    },\n    {\n      \"shape\": \"microscope slide\",\n      \"color\": \"transparent\",\n      \"size\": \"small\"\n    }\n  ],\n  \"substance_appearance\": [\n    {\n      \"color\": \"white\",\n      \"state\": \"solid\",\n      \"texture\": \"smooth\"\n    },\n    {\n      \"color\": \"black\",\n      \"state\": \"liquid\",\n      \"texture\": \"viscous\"\n    }\n  ]\n}\n```"}