{"video_id": "videos/level_1/56074/clip_39.mp4", "task": "materials", "note": "```json\n{\n  \"materials_visible\": [\n    \"FALCON tube\",\n    \"pipette tip\"\n  ],\n  \"labels_seen\": [\n    \"FALCON\",\n    \"1\"\n  ],\n  \"container_descriptions\": [\n    {\n      \"shape\": \"cylindrical\",\n      \"color\": \"transparent\",\n      \"size\": \"small\"\n    },\n    {\n      \"shape\": \"cylindrical\",\n      \"color\": \"transparent\",\n      \"size\": \"small\"\n    }\n  ],\n  \"substance_appearance\": [\n    {\n      \"color\": \"clear\",\n      \"state\": \"liquid\",\n      \"texture\": \"smooth\"\n    },\n    {\n      \"color\": \"clear\",\n      \"state\": \"liquid\",\n      \"texture\": \"smooth\"\n    }\n  ]\n}\n```"}