{"task": "video_verification", "video_path": "videos/level_2/video_verification/59447/clip_8_removed_step_4.mp4", "item_id": "59447_clip_8_video_verification", "gold": "D", "note": "```json\n{\n  \"key_evidence\": [\n    \"The video shows a person aligning a device at a 45-degree angle relative to a row of plants, indicating alignment with planting rows.\",\n    \"A spirit level is used to ensure the device is level, confirming leveling actions.\",\n    \"Connections are made between devices and a data logger, showing setup for data collection.\",\n    \"The video displays a graph with a linear relationship, but no visible calculation of a slope or regression is shown.\"\n  ],\n  \"context_observations\": [\n    \"The setup involves outdoor placement of equipment in a field with plants.\",\n    \"The person adjusts equipment on tripods and connects wires, suggesting preparation for data collection.\",\n    \"The video includes a graphical representation of data, but no explicit calculation steps are visible.\"\n  ],\n  \"salient_objects_or_text\": [\n    \"A 45-degree angle is marked on the device relative to the row orientation.\",\n    \"The text 'e.g. during full diurnal cycle' is visible, indicating a context of varying light conditions.\",\n    \"A graph with a linear trend is shown, but no visible calculation of the slope is performed.\"\n  ]\n}\n```"}