{"task": "video_verification", "video_path": "videos/level_2/video_verification/59119/clip_5_removed_step_3.mp4", "item_id": "59119_clip_5_video_verification", "gold": "C", "note": "```json\n{\n  \"key_evidence\": [\n    \"A leaf is cut from a plant and placed in a petri dish, with the petiole excluded.\",\n    \"The leaf is cut transversely from the center to the edges using a scalpel, but the pieces remain attached.\",\n    \"The petri dish is covered with a lid after the leaf is placed inside.\",\n    \"No liquid medium is visible in the petri dish, and no bacterial culture is added or stirred.\"\n  ],\n  \"context_observations\": [\n    \"The person is wearing a white lab coat and working in a laboratory setting.\",\n    \"The leaf is green and appears to be from a young plant.\",\n    \"The petri dish is transparent and placed on a white surface.\"\n  ],\n  \"salient_objects_or_text\": [\n    \"The text 'Repeat for \u226415 cv. D\u00e9sir\u00e9e or \u226425 ssp. andigena leaves' is visible on the screen.\"\n  ]\n}\n```"}