{"task": "video_verification", "video_path": "videos/level_2/video_verification/64923/clip_4_removed_step_4.mp4", "item_id": "64923_clip_4_video_verification", "gold": "D", "note": "```json\n{\n  \"key_evidence\": [\n    \"A hand is seen holding a tube labeled with a concentration of 0.25 mg/ml, which is consistent with adding a specific solution.\",\n    \"A rotating wheel is visible, indicating a step involving incubation.\",\n    \"A magnetic rack is not shown being used to remove any solution, suggesting this step was not performed.\"\n  ],\n  \"context_observations\": [\n    \"The video shows a pipette being used to transfer liquid into small tubes.\",\n    \"A centrifuge is briefly shown, indicating a step involving centrifugation.\",\n    \"The person is wearing blue gloves and handling various laboratory equipment.\"\n  ],\n  \"salient_objects_or_text\": [\n    \"The tube label reads '0.25 mg/ml'.\",\n    \"The rotating wheel has a digital display showing '15'.\",\n    \"The centrifuge has a clear lid and a white interior.\"\n  ]\n}\n```"}