{"video_id": "videos/level_1/60259/clip_19.mp4", "task": "tools", "note": "{\n  \"tools_in_use\": [\"syringe\", \"medical tubing\", \"medical pump\"],\n  \"distinguishing_features\": [\"syringe with blue plunger\", \"transparent medical tubing\", \"medical pump with digital display and control buttons\"],\n  \"labels_or_models\": [\"CME BODY GUARD\", \"PRIMING 20mL 18G FL 20/03/19\", \"20 CCM Luer-Lock Tip\"],\n  \"operating_state\": [\"syringe being filled\", \"medical tubing connected to pump\", \"medical pump appears to be on and in use\"]\n}"}