{"video_id": "videos/level_1/52653/clip_34.mp4", "task": "tools", "note": "```json\n{\n  \"tools_in_use\": [\n    \"microscope\",\n    \"surgical instruments (scissors, forceps)\",\n    \"digital timer\"\n  ],\n  \"distinguishing_features\": [\n    \"Microscope with adjustable knobs and a stage for specimen placement\",\n    \"Surgical scissors and forceps with metallic, sharp edges\",\n    \"Digital timer with a red LED display and a cylindrical body\"\n  ],\n  \"labels_or_models\": [\n    \"No visible brand or model names on the tools\"\n  ],\n  \"operating_state\": [\n    \"Microscope appears to be in use with a specimen under observation\",\n    \"Surgical instruments are laid out but not actively in use\",\n    \"Digital timer is on, displaying a countdown\"\n  ]\n}\n```"}