{"video_id": "videos/level_1/58174/clip_25.mp4", "task": "tools", "note": "```json\n{\n  \"tools_in_use\": [\n    \"microscope\",\n    \"laser alignment system\",\n    \"optical mounts\",\n    \"micrometer\"\n  ],\n  \"distinguishing_features\": [\n    \"Microscope with multiple objective lenses and a labeled LED lamp\",\n    \"Laser alignment system with a visible red laser beam\",\n    \"Optical mounts with adjustable knobs and slots for securing components\",\n    \"Micrometer for precise linear measurement\"\n  ],\n  \"labels_or_models\": [\n    \"LED LAMP\",\n    \"THORLABS\",\n    \"ULTRA\"\n  ],\n  \"operating_state\": [\n    \"Microscope appears to be in use with the LED lamp on\",\n    \"Laser alignment system is active, emitting a red laser beam\",\n    \"Optical mounts are in a fixed position, likely securing components\",\n    \"Micrometer is in a stationary position, not actively measuring\"\n  ]\n}\n```"}