{"video_id": "videos/level_1/63662/clip_31.mp4", "task": "tools", "note": "```json\n{\n  \"tools_in_use\": [\n    \"pipette\",\n    \"incubator\",\n    \"microscope\"\n  ],\n  \"distinguishing_features\": [\n    \"Pipette with a white handle and a black plunger\",\n    \"Incubator with a digital display and a glass door\",\n    \"Microscope with a binocular head and objective lenses\"\n  ],\n  \"labels_or_models\": [\n    \"Cell density: 5 \u00d7 10^5\",\n    \"WJH\"\n  ],\n  \"operating_state\": [\n    \"Pipette is in active use\",\n    \"Incubator is on, as indicated by the digital display\",\n    \"Microscope is not in use, but is present in the scene\"\n  ]\n}\n```"}