{"video_id": "videos/level_2/video_segments/62458/clip_10.mp4", "task": "sequence_generation", "note": "```json\n{\n  \"observed_steps_in_order\": [\n    \"step 1 description\",\n    \"step 2 description\"\n  ],\n  \"key_actions_per_step\": [\n    \"Analyze video footage of mice exploring objects on a computer\",\n    \"Use a mouse to interact with the computer software for data analysis\"\n  ],\n  \"materials_or_tools_used\": [\n    \"Computer with data analysis software\",\n    \"Video footage of mice exploring objects\",\n    \"Computer mouse and keyboard\"\n  ]\n}\n```"}