{"video_id": "videos/level_2/video_segments/4142/clip_9.mp4", "task": "sequence_generation", "note": "```json\n{\n  \"observed_steps_in_order\": [\n    \"Prepare and place the sample tray\",\n    \"Load the sample tray into the instrument\",\n    \"Configure the method file on the computer\"\n  ],\n  \"key_actions_per_step\": [\n    \"A gloved hand places a tray labeled 'Ethanol Standards' on the instrument\",\n    \"The tray is then loaded into the sample holder of the instrument\",\n    \"The computer screen shows a method file being selected and configured\"\n  ],\n  \"materials_or_tools_used\": [\n    \"Ethanol Standards sample tray\",\n    \"Instrument with a sample holder\",\n    \"Computer with method configuration software\"\n  ]\n}\n```"}