{"video_id": "videos/level_2/step_prediction/58334/clip_8_prediction.mp4", "task": "step_prediction", "note": "```json\n{\n  \"observed_steps\": [\n    \"A hand adjusts a syringe connected to a tube.\",\n    \"A hand uses a pipette to transfer liquid into a container.\"\n  ],\n  \"current_state_at_end\": \"The liquid has been transferred into the container using the pipette, and the hand is holding the pipette above the container.\",\n  \"next_logical_action_hint\": \"Dispose of the pipette tip or prepare for the next liquid transfer.\"\n}\n```"}