{"video_id": "videos/level_2/step_prediction/4295/clip_4_prediction.mp4", "task": "step_prediction", "note": "```json\n{\n  \"observed_steps\": [\n    \"larvae are placed on an insect diet in a container\",\n    \"the container is labeled with conditions: 16 hr light, 8 hr dark, 26\u00b0C, 2 days\",\n    \"dead or stunted larvae are sacrificed by freezing\"\n  ],\n  \"current_state_at_end\": \"the larvae are in a container with an insect diet, and the container is labeled with specific conditions\",\n  \"next_logical_action_hint\": \"monitor the larvae for 2 days under the specified light and temperature conditions\"\n}\n```"}