{"video_id": "videos/level_2/step_prediction/54863/clip_4_prediction.mp4", "task": "step_prediction", "note": "```json\n{\n  \"observed_steps\": [\n    \"A pipette is used to transfer liquid into a microtube.\",\n    \"The microtube is placed into a blue microtube rack.\",\n    \"A hand wearing a blue glove operates a thermal cycler, setting parameters on the touchscreen.\"\n  ],\n  \"current_state_at_end\": \"The thermal cycler is being programmed, likely for a PCR reaction, and the microtube is in the blue microtube rack.\",\n  \"next_logical_action_hint\": \"Close the lid of the thermal cycler and start the PCR program.\"\n}\n```"}