{"task": "experimental_conclusion", "video_path": "videos/level_3/57379_.mp4", "item_id": "57379_experimental_conclusion", "gold": ["Neat1", "Malat1", "GH4C1", "mouse pituitary"], "note": "{\n  \"key_evidence\": [\n    \"A bar graph shows enrichment of one RNA after pull-down of another RNA in both GH4C1 cells and mouse pituitary tissue.\",\n    \"The graph indicates that one RNA is significantly enriched after pull-down in the GH4C1 cell line.\",\n    \"The graph labels show two distinct RNA names being compared.\"\n  ],\n  \"context_observations\": [\n    \"The video includes a scene with a person explaining the results.\",\n    \"There is a visual of a graph with error bars indicating statistical significance.\"\n  ],\n  \"salient_objects_or_text\": [\n    \"The text 'Neat1 RNA pull-down' is visible on the screen.\",\n    \"The graph includes labels for 'GH4C1' and 'Pituitary'.\"\n  ]\n}"}