{"task": "sequence_ordering", "video_path": "videos/level_2/video_segments/57240/clip_3.mp4", "item_id": "57240_clip3_sequence_ordering", "gold": "A", "note": "```json\n{\n  \"key_evidence\": [\n    \"A hand uses a pipette to transfer a clear liquid from a tube into a small container, suggesting the addition of a solution to a sample.\",\n    \"The sample tube is then placed on a vortex mixer, which spins rapidly, indicating a mixing step.\",\n    \"The tube is later seen being placed into a centrifuge, which spins at high speed, suggesting a centrifugation step.\",\n    \"A new tube is shown being filled with a clear liquid from a pipette, likely indicating the addition of another solution.\"\n  ],\n  \"context_observations\": [\n    \"The workspace includes various laboratory equipment such as pipettes, a vortex mixer, and a centrifuge.\",\n    \"The person handling the samples is wearing blue gloves, indicating a controlled laboratory environment.\"\n  ],\n  \"salient_objects_or_text\": [\n    \"Wizard Genomic DNA Purification Kit box\",\n    \"CORNING LSE vortex mixer\",\n    \"Eppendorf centrifuge\",\n    \"Text on the centrifuge: 'Let the mixture cool to RT before proceeding'\"\n  ]\n}\n```"}