{"task": "sequence_ordering", "video_path": "videos/level_2/video_segments/58577/clip_2.mp4", "item_id": "58577_clip2_sequence_ordering", "gold": "D", "note": "```json\n{\n  \"key_evidence\": [\n    \"Water emitters are visibly placed into each pot before any other action is taken.\",\n    \"The automatic watering system is shown in operation, indicating it is used to water the pots.\",\n    \"Small depressions are created in the soil next to each plant after the watering system is set up.\",\n    \"A liquid, presumably containing nematodes, is added into the depressions after the watering system is in place.\"\n  ],\n  \"context_observations\": [\n    \"The plants are in small yellow pots with labels indicating numbers.\",\n    \"The person handling the plants is wearing blue gloves and using tools to manipulate the plants and water system.\",\n    \"The video includes text suggesting adjustments to the watering system as the plants grow.\"\n  ],\n  \"salient_objects_or_text\": [\n    \"Yellow pots with numerical labels like '504', '512', and '571'.\",\n    \"Water emitters and white tubing connected to the pots.\",\n    \"Text on screen mentioning adjustments to the watering system.\"\n  ]\n}\n```"}