{"video_id": "videos/level_2/video_verification/56437/clip_1_removed_step_2.mp4", "task": "video_verification", "note": "```json\n{\n  \"steps_actually_shown\": [\n    \"Open a bottle labeled 'NBM'.\",\n    \"Pour liquid from a graduated cylinder into the bottle.\",\n    \"Close the bottle with a blue cap.\",\n    \"Place the bottle into a centrifuge.\"\n  ],\n  \"missing_or_skipped\": \"The video does not show the centrifugation process or the removal of the bottle after centrifugation.\",\n  \"key_objects_handled\": [\n    \"Bottle labeled 'NBM'\",\n    \"Graduated cylinder\",\n    \"Blue cap\",\n    \"Centrifuge\"\n  ]\n}\n```"}