{"video_id": "videos/level_3/55307_.mp4", "task": "scientific_discovery", "note": "```json\n{\n  \"experiment_overview\": \"The experiment focuses on monovalent cation doping of CH3NH3PbI3 to enhance the efficiency of perovskite solar cells.\",\n  \"novel_techniques_shown\": [\"Monovalent cation doping technique\", \"Use of various dopants like CuBr, NaI, and AgI\"],\n  \"key_steps\": [\n    \"Mixing of dopant solutions using a pipette\",\n    \"Loading the solution into a vial\",\n    \"Stirring the solution in a magnetic stirrer\",\n    \"Analyzing the material properties using X-ray diffraction (XRD) and other spectroscopic techniques\"\n  ],\n  \"materials_subjects\": [\"CH3NH3PbI3 perovskite material\", \"Dopants: CuBr, NaI, AgI\"],\n  \"tools_and_setup\": [\n    \"Pipette for precise liquid handling\",\n    \"Vials for storing solutions\",\n    \"Magnetic stirrer for mixing solutions\",\n    \"X-ray diffractometer for material analysis\",\n    \"Spectroscopic instruments for performance evaluation\"\n  ],\n  \"anything_unusual_or_notable\": [\"The use of different dopants to optimize the performance of perovskite solar cells\"]\n}\n```"}