{"video_id": "videos/level_3/3608_.mp4", "task": "scientific_discovery", "note": "```json\n{\n  \"experiment_overview\": \"The experiment involves preparing and encapsulating human embryonic stem cells (hESC) using alginate, followed by culturing them under specific conditions to study their proliferation and expression levels.\",\n  \"novel_techniques_shown\": [\"Alginate encapsulation\", \"Culturing hESC in SR media with ROCK inhibitor\", \"BrdU staining for cell proliferation analysis\", \"TUNEL assay for apoptosis detection\"],\n  \"key_steps\": [\n    \"Preparation of 1.1% Alginate solution\",\n    \"Encapsulation of hESC in alginate\",\n    \"Centrifugation at 95 x g for 5 minutes\",\n    \"Incubation at 37\u00b0C with 5% CO2\",\n    \"Washing twice with D PBS\",\n    \"Culturing in SR media with ROCK inhibitor\",\n    \"Staining with BrdU for cell proliferation analysis\",\n    \"Performing TUNEL assay for apoptosis detection\"\n  ],\n  \"materials_subjects\": [\"Human embryonic stem cells (hESC)\", \"Alginate\", \"SR media\", \"ROCK inhibitor\", \"D PBS\", \"BrdU\", \"TUNEL reagents\"],\n  \"tools_and_setup\": [\n    \"Orbital mixer\",\n    \"Centrifuge\",\n    \"Incubator\",\n    \"Microscope\",\n    \"Microscope slides\",\n    \"Microscope objective lenses\",\n    \"Microscope filters\",\n    \"Microscope camera\"\n  ],\n  \"anything_unusual_or_notable\": [\"The use of ROCK inhibitor to modulate cell proliferation and apoptosis, which is a significant aspect of the study as it helps in understanding the role of this inhibitor in hESC culture.\"]\n}\n```"}